pyo365/__init__.py
pyo365/account.py
pyo365/address_book.py
pyo365/calendar.py
pyo365/connection.py
pyo365/drive.py
pyo365/mailbox.py
pyo365/message.py
pyo365/utils/__init__.py
pyo365/utils/attachment.py
pyo365/utils/utils.py
pyo365/utils/windows_tz.py
pyo365-0.1.3.dist-info/LICENSE
pyo365-0.1.3.dist-info/METADATA
pyo365-0.1.3.dist-info/WHEEL
pyo365-0.1.3.dist-info/top_level.txt
pyo365-0.1.3.dist-info/RECORD
