Metadata-Version: 2.1
Name: pyo365
Version: 0.1.3
Summary: A simple python library to interact with Microsoft Graph and Office 365 API
Home-page: https://github.com/janscas/pyo365
Author: Janscas
Author-email: janscas@users.noreply.github.com
Maintainer: Janscas
Maintainer-email: janscas@users.noreply.github.com
License: Apache License 2.0
Platform: UNKNOWN
Classifier: Development Status :: 4 - Beta
Classifier: Intended Audience :: Developers
Classifier: License :: OSI Approved :: Apache Software License
Classifier: Topic :: Office/Business :: Office Suites
Classifier: Topic :: Software Development :: Libraries
Classifier: Programming Language :: Python
Classifier: Programming Language :: Python :: 3 :: Only
Classifier: Programming Language :: Python :: 3.4
Classifier: Programming Language :: Python :: 3.5
Classifier: Programming Language :: Python :: 3.6
Classifier: Programming Language :: Python :: 3.7
Classifier: Programming Language :: Python :: 3.8
Classifier: Operating System :: OS Independent
Requires-Python: >=3.4
Requires-Dist: requests (>=2.0.0)
Requires-Dist: requests-oauthlib (>=1.0.0)
Requires-Dist: python-dateutil (>=2.7)
Requires-Dist: pytz (>=2018.5)
Requires-Dist: tzlocal (>=1.5.0)
Requires-Dist: beautifulsoup4 (>=4.0.0)
Requires-Dist: stringcase (>=1.2.0)
